infi.recipe.close_application-0.0.18-py2.7-nspkg.pth
infi/recipe/close_application/__init__.py
infi/recipe/close_application/__version__.py
infi/recipe/close_application/tests.py
infi.recipe.close_application-0.0.18.dist-info/LICENSE
infi.recipe.close_application-0.0.18.dist-info/METADATA
infi.recipe.close_application-0.0.18.dist-info/WHEEL
infi.recipe.close_application-0.0.18.dist-info/entry_points.txt
infi.recipe.close_application-0.0.18.dist-info/namespace_packages.txt
infi.recipe.close_application-0.0.18.dist-info/top_level.txt
infi.recipe.close_application-0.0.18.dist-info/RECORD
