Metadata-Version: 2.1
Name: infi.recipe.close-application
Version: 0.0.18
Summary: buildout recipe for terminating all executables
Home-page: https://github.com/Infinidat/infi.recipe.close_application
Author: Arnon Yaari
Author-email: arnony@infinidat.com
License: BSD
Platform: UNKNOWN
Classifier: Intended Audience :: Developers
Classifier: Intended Audience :: System Administrators
Classifier: License :: OSI Approved :: BSD License
Classifier: Operating System :: OS Independent
Classifier: Programming Language :: Python :: 2
Classifier: Programming Language :: Python :: 3
Classifier: Topic :: Software Development :: Libraries :: Python Modules
Requires-Dist: psutil (>=2.0)
Requires-Dist: setuptools
Requires-Dist: zc.buildout
